sklearnPra/__init__.py
sklearnPra/code.py
sklearnPra/helper.py
sklearnPra/main.py
sklearnPrac/__init__.py
sklearnPrac/code.py
sklearnprac-0.1.dist-info/LICENSE
sklearnprac-0.1.dist-info/METADATA
sklearnprac-0.1.dist-info/WHEEL
sklearnprac-0.1.dist-info/top_level.txt
sklearnprac-0.1.dist-info/RECORD
